mycalc/calculator.py
juseokson2024193-1.0.1.dist-info/METADATA
juseokson2024193-1.0.1.dist-info/WHEEL
juseokson2024193-1.0.1.dist-info/top_level.txt
juseokson2024193-1.0.1.dist-info/RECORD
