Metadata-Version: 2.1
Name: juseokson2024193
Version: 1.0.1
Summary: nice calc
Home-page: http://github.com/snSon/abc
Download-URL: http://github.com/snSon/abc/
Author: sonjuseok
License: UNKNOWN
Platform: UNKNOWN
